magichue/__init__.py
magichue/bulb_types.py
magichue/commands.py
magichue/discover.py
magichue/exceptions.py
magichue/http_api.py
magichue/light.py
magichue/magichue.py
magichue/modes.py
magichue/utils.py
python_magichue-0.3.2.dist-info/LICENSE
python_magichue-0.3.2.dist-info/METADATA
python_magichue-0.3.2.dist-info/WHEEL
python_magichue-0.3.2.dist-info/top_level.txt
python_magichue-0.3.2.dist-info/RECORD
