Metadata-Version: 2.1
Name: python-magichue
Version: 0.3.2
Summary: A library to interface with Magichue(or Magichome)
Home-page: https://github.com/namacha/python-magichue
Author: namacha
Author-email: mac.ayu15@gmail.com
License: MIT
Platform: UNKNOWN
Classifier: Development Status :: 2 - Pre-Alpha
Classifier: Environment :: Other Environment
Classifier: Intended Audience :: Developers
Classifier: Intended Audience :: Education
Classifier: License :: OSI Approved :: MIT License
Classifier: Operating System :: Microsoft :: Windows
Classifier: Operating System :: MacOS
Classifier: Operating System :: POSIX :: Linux
Classifier: Programming Language :: Python :: 3
Classifier: Topic :: Home Automation
